Workbook
Name conversionRate: Assumptions!$B$38
Name pctBuyingExtra: Assumptions!$B$37
Name storageBlockGB: Assumptions!$B$35
Name storageBlockPrice: Assumptions!$B$36
Name storageIncludedGB: Assumptions!$B$34
Name yr1Price: Assumptions!$B$32
Name yr2Price: Assumptions!$B$33

Sheet Assumptions
A1: Would You Please — Hosting Cost Crossover Model
A2: Assumptions. Blue cells are editable inputs. All dollar figures in this workbook are 2026 list prices, pre-discount.
A4: 1. Activity assumptions — from the PRD (§6.2.1, v12.9)
A5: Items (Requests + ToDos) per user per day | B5: 0.5 | C5: PRD §6.2.1 — linear across Pilot/Year 1/Long-Term (5,000/10,000 = 50,000/100,000 = 500,000/1,000,000 = 0.5)
A6: Dialog entries per user per day | B6: 0.3 | C6: PRD §6.2.1 — linear across all three anchors (0.3/user/day)
A7: Notification emails per user per day (at or below 100,000 users) | B7: 1.05 | C7: PRD §6.2.1 Pilot/Year 1 anchors: 10,500/10,000 = 105,000/100,000 = 1.05/user/day
A8: SMS per user per day (at or below 100,000 users) | B8: 0.025 | C8: PRD §6.2.1 Pilot/Year 1 anchors: 250/10,000 = 2,500/100,000 = 0.025/user/day
A9: Notification emails/day at 1,000,000 users | B9: 260000 | C9: PRD §6.2.1 Long-Term anchor — NOT linear; PRD notes most notifications shift to mobile push after Phase 1
A10: SMS/day at 1,000,000 users | B10: 5000 | C10: PRD §6.2.1 Long-Term anchor — NOT linear; push-first at scale, and Text delivery is a paid-subscriber-only feature from v12.2
A11: Attachment storage per user, Pilot (GB/user) | B11: 0.05 | C11: PRD §6.2.1: 0.5 TB / 10,000 users
A12: Attachment storage per user, Year 1 (GB/user) | B12: 0.02 | C12: PRD §6.2.1: 2 TB / 100,000 users (per-user figure falls — S3 lifecycle tiering assumed)
A13: Attachment storage, Long-Term TOTAL (GB) | B13: 30000 | C13: PRD §6.2.1: midpoint of the PRD's own 20–40 TB Long-Term range
A14: Monthly-active share of registered users | B14: 0.6 | C14: PRD §6.2 modeling assumption: 50–70% range; midpoint used here
A15: Planning-uncertainty band (± around the base estimate) | B15: 0.5 | C15: Matches the PRD's own stated accuracy for its AWS estimate (“planning-level, roughly plus/minus 50%”) — applied symmetrically to the Vercel/Supabase side here so the two stacks are compared on the same footing
A17: 2. Vercel technical assumptions — NOT in the PRD (the PRD modeled AWS EC2/RDS, not a serverless host). These are new planning-level estimates; replace with real figures from Vercel's own Usage dashboard once there is real traffic.
A18: Data transfer per Monthly Active User per month (MB) | B18: 20 | C18: Planning estimate for a lean, mostly-JSON/text app — most static assets are CDN/browser-cached after first visit
A19: Function invocations per Item/Dialog action | B19: 4 | C19: Planning estimate — create/save/list/detail round trips generated by one action
A20: Baseline function invocations per MAU per month | B20: 150 | C20: Planning estimate — navigation, search, list refreshes not tied to a specific item
A21: Edge requests per function invocation | B21: 2 | C21: Planning estimate — static asset + middleware requests alongside each function call
A22: Avg active CPU time per invocation (seconds) | B22: 0.15 | C22: Planning estimate for a lean Node.js API route / SSR render
A23: Avg provisioned memory per function (GB) | B23: 0.5 | C23: Planning estimate (512 MB functions)
A24: Vercel developer seats | B24: 1 | C24: Solo developer today — raise if the team grows; cost is flat per seat, not per user
A26: 3. Supabase technical assumptions — also new planning-level estimates, not in the PRD.
A27: Avg DB row size incl. indexes, items+dialog rows (KB) | B27: 2 | C27: Planning estimate
A28: Per-user fixed DB overhead — profile, contacts, settings (KB) | B28: 5 | C28: Planning estimate
A29: DB egress per MAU per month (MB) | B29: 10 | C29: Planning estimate — raw query payload Supabase serves to the Vercel functions, smaller than client-facing bandwidth since it precedes JSON shaping/compression
A31: 4. Subscriber pricing & storage — Jim's revision, 2026-08-24 (supersedes the PRD's own $17.95/yr flat figure)
A32: Year 1 subscription price | B32: 17.95 | C32: Jim's own figure — 25% off $23.95 is actually $17.96, a one-cent difference, not corrected here.
A33: Year 2+ (renewal) subscription price | B33: 23.95
A34: Storage included per subscriber (GB) | B34: 5
A35: Additional storage block size (GB) | B35: 5
A36: Additional storage price per block / year | B36: 10
A37: Subscribers buying additional storage | B37: 0.05 | C37: Assumption, not confirmed by Jim — easy to change here.
A38: Free-to-paid conversion rate (registered users) | B38: 0.03 | C38: Typical freemium SaaS range 2-5%; not a WYP-specific measurement — no real user base yet to measure from.

Sheet User Tiers
A1: Derived usage volumes by registered-user tier
A2: 1,000 and 50,000 are added beyond the PRD's own three anchors (10,000 / 100,000 / 1,000,000), interpolated as noted per row.
A3: Metric | B3: 1,000 | C3: 10,000 (Pilot) | D3: 50,000 | E3: 100,000 (Year 1) | F3: 1,000,000 (Long-Term)
A4: Registered users | B4: 1000 | C4: 10000 | D4: 50000 | E4: 100000 | F4: 1000000
A5: Items (Requests + ToDos) / day | B5: =B4*Assumptions!$B$5 -> 500 | C5: =C4*Assumptions!$B$5 -> 5000 | D5: =D4*Assumptions!$B$5 -> 25000 | E5: =E4*Assumptions!$B$5 -> 50000 | F5: =F4*Assumptions!$B$5 -> 500000
A6: Dialog entries / day | B6: =B4*Assumptions!$B$6 -> 300 | C6: =C4*Assumptions!$B$6 -> 3000 | D6: =D4*Assumptions!$B$6 -> 15000 | E6: =E4*Assumptions!$B$6 -> 30000 | F6: =F4*Assumptions!$B$6 -> 300000
A7: Notification emails / day | B7: =B4*Assumptions!$B$7 -> 1050 | C7: =C4*Assumptions!$B$7 -> 10500 | D7: =D4*Assumptions!$B$7 -> 52500 | E7: =E4*Assumptions!$B$7 -> 105000 | F7: =Assumptions!$B$9 -> 260000
A8: SMS / day | B8: =B4*Assumptions!$B$8 -> 25 | C8: =C4*Assumptions!$B$8 -> 250 | D8: =D4*Assumptions!$B$8 -> 1250 | E8: =E4*Assumptions!$B$8 -> 2500 | F8: =Assumptions!$B$10 -> 5000
A9: Monthly Active Users (MAU) | B9: =B4*Assumptions!$B$14 -> 600 | C9: =C4*Assumptions!$B$14 -> 6000 | D9: =D4*Assumptions!$B$14 -> 30000 | E9: =E4*Assumptions!$B$14 -> 60000 | F9: =F4*Assumptions!$B$14 -> 600000
A10: Attachment/Location storage (GB) | B10: =B4*Assumptions!$B$11 -> 50 | C10: =C4*Assumptions!$B$11 -> 500 | D10: =D4*(Assumptions!$B$11+(Assumptions!$B$12-Assumptions!$B$11)*(LOG10(D4)-LOG10(C4))/(LOG10(E4)-LOG10(C4))) -> 1451.545 | E10: =E4*Assumptions!$B$12 -> 2000 | F10: =Assumptions!$B$13 -> 30000
A12: Row 10 (50,000-user column) interpolates the per-user storage rate on a log10(users) scale between the Pilot and Year 1 anchors — a standard technique for order-of-magnitude planning between two known points, not a PRD figure.

Sheet Vercel Cost Model
A1: Vercel cost model (Pro plan, 2026 list pricing)
A2: Source: vercel.com/pricing, fetched 2026-08-14. $20/mo per seat + $20 usage credit; overage billed as shown below.
A3: Metric | B3: 1,000 | C3: 10,000 (Pilot) | D3: 50,000 | E3: 100,000 (Year 1) | F3: 1,000,000 (Long-Term)
A4: Registered users | B4: ='User Tiers'!B4 -> 1000 | C4: ='User Tiers'!C4 -> 10000 | D4: ='User Tiers'!D4 -> 50000 | E4: ='User Tiers'!E4 -> 100000 | F4: ='User Tiers'!F4 -> 1000000
A5: Monthly function invocations | B5: =(('User Tiers'!B$5+'User Tiers'!B$6)*30*Assumptions!$B$19)+('User Tiers'!B$9*Assumptions!$B$20) -> 186000 | C5: =(('User Tiers'!C$5+'User Tiers'!C$6)*30*Assumptions!$B$19)+('User Tiers'!C$9*Assumptions!$B$20) -> 1860000 | D5: =(('User Tiers'!D$5+'User Tiers'!D$6)*30*Assumptions!$B$19)+('User Tiers'!D$9*Assumptions!$B$20) -> 9300000 | E5: =(('User Tiers'!E$5+'User Tiers'!E$6)*30*Assumptions!$B$19)+('User Tiers'!E$9*Assumptions!$B$20) -> 18600000 | F5: =(('User Tiers'!F$5+'User Tiers'!F$6)*30*Assumptions!$B$19)+('User Tiers'!F$9*Assumptions!$B$20) -> 186000000
A6: Monthly edge requests | B6: =B5*Assumptions!$B$21 -> 372000 | C6: =C5*Assumptions!$B$21 -> 3720000 | D6: =D5*Assumptions!$B$21 -> 18600000 | E6: =E5*Assumptions!$B$21 -> 37200000 | F6: =F5*Assumptions!$B$21 -> 372000000
A7: Monthly data transfer (GB) | B7: =('User Tiers'!B$9*Assumptions!$B$18)/1024 -> 11.71875 | C7: =('User Tiers'!C$9*Assumptions!$B$18)/1024 -> 117.1875 | D7: =('User Tiers'!D$9*Assumptions!$B$18)/1024 -> 585.9375 | E7: =('User Tiers'!E$9*Assumptions!$B$18)/1024 -> 1171.875 | F7: =('User Tiers'!F$9*Assumptions!$B$18)/1024 -> 11718.75
A8: Monthly compute (provisioned-memory GB-hours) | B8: =B5*Assumptions!$B$22*Assumptions!$B$23/3600 -> 3.875 | C8: =C5*Assumptions!$B$22*Assumptions!$B$23/3600 -> 38.75 | D8: =D5*Assumptions!$B$22*Assumptions!$B$23/3600 -> 193.75 | E8: =E5*Assumptions!$B$22*Assumptions!$B$23/3600 -> 387.5 | F8: =F5*Assumptions!$B$22*Assumptions!$B$23/3600 -> 3875
A10: Cost components ($/month)
A11: Seats — $20/mo × seats | B11: =Assumptions!$B$24*20 -> 20 | C11: =Assumptions!$B$24*20 -> 20 | D11: =Assumptions!$B$24*20 -> 20 | E11: =Assumptions!$B$24*20 -> 20 | F11: =Assumptions!$B$24*20 -> 20
A12: Bandwidth overage — >1,000 GB @ $0.15/GB | B12: =MAX(0,B7-1000)*0.15 -> 0 | C12: =MAX(0,C7-1000)*0.15 -> 0 | D12: =MAX(0,D7-1000)*0.15 -> 0 | E12: =MAX(0,E7-1000)*0.15 -> 25.78125 | F12: =MAX(0,F7-1000)*0.15 -> 1607.8125
A13: Edge request overage — >10M @ $2/1M | B13: =MAX(0,B6-10000000)/1000000*2 -> 0 | C13: =MAX(0,C6-10000000)/1000000*2 -> 0 | D13: =MAX(0,D6-10000000)/1000000*2 -> 17.2 | E13: =MAX(0,E6-10000000)/1000000*2 -> 54.4 | F13: =MAX(0,F6-10000000)/1000000*2 -> 724
A14: Function invocation overage — >1M @ $0.60/1M | B14: =MAX(0,B5-1000000)/1000000*0.6 -> 0 | C14: =MAX(0,C5-1000000)/1000000*0.6 -> 0.516 | D14: =MAX(0,D5-1000000)/1000000*0.6 -> 4.98 | E14: =MAX(0,E5-1000000)/1000000*0.6 -> 10.56 | F14: =MAX(0,F5-1000000)/1000000*0.6 -> 111
A15: Compute — GB-hours @ $0.0106/GB-hr | B15: =B8*0.0106 -> 0.041075 | C15: =C8*0.0106 -> 0.41075 | D15: =D8*0.0106 -> 2.05375 | E15: =E8*0.0106 -> 4.1075 | F15: =F8*0.0106 -> 41.075
A17: Vercel monthly total — base estimate | B17: =SUM(B11:B15) -> 20.041075 | C17: =SUM(C11:C15) -> 20.92675 | D17: =SUM(D11:D15) -> 44.23375 | E17: =SUM(E11:E15) -> 114.84875 | F17: =SUM(F11:F15) -> 2503.8875
A18: Vercel monthly — LOW (base × (1 − uncertainty)) | B18: =B17*(1-Assumptions!$B$15) -> 10.020537 | C18: =C17*(1-Assumptions!$B$15) -> 10.463375 | D18: =D17*(1-Assumptions!$B$15) -> 22.116875 | E18: =E17*(1-Assumptions!$B$15) -> 57.424375 | F18: =F17*(1-Assumptions!$B$15) -> 1251.9437
A19: Vercel monthly — HIGH (base × (1 + uncertainty)) | B19: =B17*(1+Assumptions!$B$15) -> 30.061612 | C19: =C17*(1+Assumptions!$B$15) -> 31.390125 | D19: =D17*(1+Assumptions!$B$15) -> 66.350625 | E19: =E17*(1+Assumptions!$B$15) -> 172.27313 | F19: =F17*(1+Assumptions!$B$15) -> 3755.8312
A20: Vercel ANNUAL — LOW | B20: =B18*12 -> 120.24645 | C20: =C18*12 -> 125.5605 | D20: =D18*12 -> 265.4025 | E20: =E18*12 -> 689.0925 | F20: =F18*12 -> 15023.325
A21: Vercel ANNUAL — HIGH | B21: =B19*12 -> 360.73935 | C21: =C19*12 -> 376.6815 | D21: =D19*12 -> 796.2075 | E21: =E19*12 -> 2067.2775 | F21: =F19*12 -> 45069.975

Sheet Supabase Cost Model
A1: Supabase cost model (Pro plan, 2026 list pricing)
A2: Source: supabase.com/pricing, fetched 2026-08-14. $25/mo base + compute add-on + metered overage. | H2: Compute tier breakpoints (edit to adjust sizing)
A3: Metric | B3: 1,000 | C3: 10,000 (Pilot) | D3: 50,000 | E3: 100,000 (Year 1) | F3: 1,000,000 (Long-Term) | H3: Users ≥ | I3: Tier | J3: $/mo
A4: Registered users | B4: ='User Tiers'!B4 -> 1000 | C4: ='User Tiers'!C4 -> 10000 | D4: ='User Tiers'!D4 -> 50000 | E4: ='User Tiers'!E4 -> 100000 | F4: ='User Tiers'!F4 -> 1000000 | H4: 0 | I4: Micro | J4: 10
A5: Compute tier price ($/mo) | B5: =INDEX($J$4:$J$9,MATCH(B4,$H$4:$H$9,1)) -> 10 | C5: =INDEX($J$4:$J$9,MATCH(C4,$H$4:$H$9,1)) -> 10 | D5: =INDEX($J$4:$J$9,MATCH(D4,$H$4:$H$9,1)) -> 15 | E5: =INDEX($J$4:$J$9,MATCH(E4,$H$4:$H$9,1)) -> 60 | F5: =INDEX($J$4:$J$9,MATCH(F4,$H$4:$H$9,1)) -> 410 | H5: 20000 | I5: Small | J5: 15
A6: Compute — net of $10/mo credit | B6: =MAX(0,B5-10) -> 0 | C6: =MAX(0,C5-10) -> 0 | D6: =MAX(0,D5-10) -> 5 | E6: =MAX(0,E5-10) -> 50 | F6: =MAX(0,F5-10) -> 400 | H6: 75000 | I6: Medium | J6: 60
A7: MAU | B7: ='User Tiers'!B$9 -> 600 | C7: ='User Tiers'!C$9 -> 6000 | D7: ='User Tiers'!D$9 -> 30000 | E7: ='User Tiers'!E$9 -> 60000 | F7: ='User Tiers'!F$9 -> 600000 | H7: 250000 | I7: Large | J7: 110
A8: MAU overage — >100,000 @ $0.00325 | B8: =MAX(0,B7-100000)*0.00325 -> 0 | C8: =MAX(0,C7-100000)*0.00325 -> 0 | D8: =MAX(0,D7-100000)*0.00325 -> 0 | E8: =MAX(0,E7-100000)*0.00325 -> 0 | F8: =MAX(0,F7-100000)*0.00325 -> 1625 | H8: 600000 | I8: XL | J8: 210
A9: Estimated DB size (GB) | B9: =(('User Tiers'!B$5+'User Tiers'!B$6)*365*Assumptions!$B$27/1000000)+('User Tiers'!B$4*Assumptions!$B$28/1000000) -> 0.589 | C9: =(('User Tiers'!C$5+'User Tiers'!C$6)*365*Assumptions!$B$27/1000000)+('User Tiers'!C$4*Assumptions!$B$28/1000000) -> 5.89 | D9: =(('User Tiers'!D$5+'User Tiers'!D$6)*365*Assumptions!$B$27/1000000)+('User Tiers'!D$4*Assumptions!$B$28/1000000) -> 29.45 | E9: =(('User Tiers'!E$5+'User Tiers'!E$6)*365*Assumptions!$B$27/1000000)+('User Tiers'!E$4*Assumptions!$B$28/1000000) -> 58.9 | F9: =(('User Tiers'!F$5+'User Tiers'!F$6)*365*Assumptions!$B$27/1000000)+('User Tiers'!F$4*Assumptions!$B$28/1000000) -> 589 | H9: 1000000 | I9: 2XL | J9: 410
A10: Disk overage — >8 GB @ $0.125/GB | B10: =MAX(0,B9-8)*0.125 -> 0 | C10: =MAX(0,C9-8)*0.125 -> 0 | D10: =MAX(0,D9-8)*0.125 -> 2.68125 | E10: =MAX(0,E9-8)*0.125 -> 6.3625 | F10: =MAX(0,F9-8)*0.125 -> 72.625
A11: DB egress (GB/month) | B11: =(B7*Assumptions!$B$29)/1024 -> 5.859375 | C11: =(C7*Assumptions!$B$29)/1024 -> 58.59375 | D11: =(D7*Assumptions!$B$29)/1024 -> 292.96875 | E11: =(E7*Assumptions!$B$29)/1024 -> 585.9375 | F11: =(F7*Assumptions!$B$29)/1024 -> 5859.375 | H11: Rough sizing guess, not a load test. Real compute needs depend on query patterns, not just user count.
A12: Egress overage — >250 GB @ $0.09/GB | B12: =MAX(0,B11-250)*0.09 -> 0 | C12: =MAX(0,C11-250)*0.09 -> 0 | D12: =MAX(0,D11-250)*0.09 -> 3.8671875 | E12: =MAX(0,E11-250)*0.09 -> 30.234375 | F12: =MAX(0,F11-250)*0.09 -> 504.84375
A13: Attachment/Location storage (GB) | B13: ='User Tiers'!B$10 -> 50 | C13: ='User Tiers'!C$10 -> 500 | D13: ='User Tiers'!D$10 -> 1451.545 | E13: ='User Tiers'!E$10 -> 2000 | F13: ='User Tiers'!F$10 -> 30000
A14: File-storage overage — >100 GB @ $0.0213/GB | B14: =MAX(0,B13-100)*0.0213 -> 0 | C14: =MAX(0,C13-100)*0.0213 -> 8.52 | D14: =MAX(0,D13-100)*0.0213 -> 28.787908 | E14: =MAX(0,E13-100)*0.0213 -> 40.47 | F14: =MAX(0,F13-100)*0.0213 -> 636.87
A16: Supabase base plan ($/mo) | B16: 25 | C16: 25 | D16: 25 | E16: 25 | F16: 25
A17: Supabase monthly total — base estimate | B17: =B16+B6+B8+B10+B12+B14 -> 25 | C17: =C16+C6+C8+C10+C12+C14 -> 33.52 | D17: =D16+D6+D8+D10+D12+D14 -> 65.336346 | E17: =E16+E6+E8+E10+E12+E14 -> 152.06687 | F17: =F16+F6+F8+F10+F12+F14 -> 3264.3387
A18: Supabase monthly — LOW | B18: =B17*(1-Assumptions!$B$15) -> 12.5 | C18: =C17*(1-Assumptions!$B$15) -> 16.76 | D18: =D17*(1-Assumptions!$B$15) -> 32.668173 | E18: =E17*(1-Assumptions!$B$15) -> 76.033437 | F18: =F17*(1-Assumptions!$B$15) -> 1632.1694
A19: Supabase monthly — HIGH | B19: =B17*(1+Assumptions!$B$15) -> 37.5 | C19: =C17*(1+Assumptions!$B$15) -> 50.28 | D19: =D17*(1+Assumptions!$B$15) -> 98.004519 | E19: =E17*(1+Assumptions!$B$15) -> 228.10031 | F19: =F17*(1+Assumptions!$B$15) -> 4896.5081
A20: Supabase ANNUAL — LOW | B20: =B18*12 -> 150 | C20: =C18*12 -> 201.12 | D20: =D18*12 -> 392.01808 | E20: =E18*12 -> 912.40125 | F20: =F18*12 -> 19586.033
A21: Supabase ANNUAL — HIGH | B21: =B19*12 -> 450 | C21: =C19*12 -> 603.36 | D21: =D19*12 -> 1176.0542 | E21: =E19*12 -> 2737.2037 | F21: =F19*12 -> 58758.098
A23: At very large scale, Supabase's Team plan ($599/mo base) adds SOC2/ISO27001 and priority SLAs that may matter for a large user base independent of the metered costs above — not included here.

Sheet Subscriber Revenue
A1: Subscriber revenue, by registered-user tier
A2: Subscriber count = registered users x conversion rate (Assumptions sheet). Two pricing cases shown: 'Year 1' (every subscriber just signed up, at the discounted price) and 'Renewal' (every subscriber is in a steady-state renewal year) — real revenue in any given year sits between these two bounds, same LOW/HIGH-bracket convention as the Vercel/Supabase cost sheets.
A4: Metric | B4: 1,000 | C4: 10,000 (Pilot) | D4: 50,000 | E4: 100,000 (Year 1) | F4: 1,000,000 (Long-Term)
A5: Registered users | B5: ='User Tiers'!B4 -> 1000 | C5: ='User Tiers'!C4 -> 10000 | D5: ='User Tiers'!D4 -> 50000 | E5: ='User Tiers'!E4 -> 100000 | F5: ='User Tiers'!F4 -> 1000000
A6: Subscribers (registered users x conversion rate) | B6: =B5*conversionRate -> 30 | C6: =C5*conversionRate -> 300 | D6: =D5*conversionRate -> 1500 | E6: =E5*conversionRate -> 3000 | F6: =F5*conversionRate -> 30000
A8: Subscription revenue — Year 1 pricing | B8: =B6*yr1Price -> 538.5 | C8: =C6*yr1Price -> 5385 | D8: =D6*yr1Price -> 26925 | E8: =E6*yr1Price -> 53850 | F8: =F6*yr1Price -> 538500
A9: Subscription revenue — Renewal pricing | B9: =B6*yr2Price -> 718.5 | C9: =C6*yr2Price -> 7185 | D9: =D6*yr2Price -> 35925 | E9: =E6*yr2Price -> 71850 | F9: =F6*yr2Price -> 718500
A10: Additional-storage revenue (expected value) | B10: =B6*pctBuyingExtra*storageBlockPrice -> 15 | C10: =C6*pctBuyingExtra*storageBlockPrice -> 150 | D10: =D6*pctBuyingExtra*storageBlockPrice -> 750 | E10: =E6*pctBuyingExtra*storageBlockPrice -> 1500 | F10: =F6*pctBuyingExtra*storageBlockPrice -> 15000
A12: TOTAL revenue — Year 1 pricing case | B12: =B8+B10 -> 553.5 | C12: =C8+C10 -> 5535 | D12: =D8+D10 -> 27675 | E12: =E8+E10 -> 55350 | F12: =F8+F10 -> 553500
A13: TOTAL revenue — Renewal pricing case | B13: =B9+B10 -> 733.5 | C13: =C9+C10 -> 7335 | D13: =D9+D10 -> 36675 | E13: =E9+E10 -> 73350 | F13: =F9+F10 -> 733500
A15: Marginal storage cost added by 5GB-included allotment (Supabase overage, once the pooled 100GB is exceeded)
A16: Subscriber storage demand (GB, at 5GB included each) | B16: =B6*storageIncludedGB -> 150 | C16: =C6*storageIncludedGB -> 1500 | D16: =D6*storageIncludedGB -> 7500 | E16: =E6*storageIncludedGB -> 15000 | F16: =F6*storageIncludedGB -> 150000
A17: Storage overage cost/yr (subscriber demand vs. Supabase's pooled 100GB) | B17: =MAX(0,B16-100)*0.0213*12 -> 12.78 | C17: =MAX(0,C16-100)*0.0213*12 -> 357.84 | D17: =MAX(0,D16-100)*0.0213*12 -> 1891.44 | E17: =MAX(0,E16-100)*0.0213*12 -> 3808.44 | F17: =MAX(0,F16-100)*0.0213*12 -> 38314.44

Sheet AWS (PRD sec 6.2)
A1: AWS cost reference — from the PRD's own model
A2: Source: WouldYouPlease_PRD_v12_9.docx §6.2.2, “planning-level estimates, accuracy roughly plus/minus 50%, AWS us-east-1 on-demand pricing as of mid-2026, before AWS Activate credits or reserved-instance discounts.”
A3: Metric | B3: 1,000 | C3: 10,000 (Pilot) | D3: 50,000 | E3: 100,000 (Year 1) | F3: 1,000,000 (Long-Term)
A4: Registered users | B4: 1000 | C4: 10000 | D4: 50000 | E4: 100000 | F4: 1000000
A6: AWS ANNUAL — LOW ($) | B6: =C6 -> 4400 | C6: 4400 | D6: =C6+(E6-C6)*(LOG10(D4)-LOG10(C4))/(LOG10(E4)-LOG10(C4)) -> 17400.842 | E6: 23000 | F6: 100000
A7: AWS ANNUAL — HIGH ($) | B7: =C7 -> 7900 | C7: 7900 | D7: =C7+(E7-C7)*(LOG10(D4)-LOG10(C4))/(LOG10(E4)-LOG10(C4)) -> 29637.967 | E7: 39000 | F7: 180000
A9: 1,000-user column: AWS's architecture in the PRD is always-on EC2 + RDS + ElastiCache, sized to the Pilot's own 10,000-user ceiling — that fixed floor doesn't shrink much below 10,000 real users, unlike Vercel/Supabase's metered, scale-to-near-zero model. 50,000-user column: log-interpolated between the Pilot and Year 1 anchors — not a PRD figure.

Sheet Crossover Summary
A1: Crossover summary — AWS (PRD) vs. Vercel + Supabase, annual cost
A2: All figures annualized, list pricing, before any AWS Activate credits. See each cost-model tab for the build-up.
A4: Registered users | B4: AWS — LOW | C4: AWS — HIGH | D4: AWS — MID | E4: Vercel+Supabase — LOW | F4: Vercel+Supabase — HIGH | G4: Vercel+Supabase — MID | H4: AWS ÷ Vercel+Supabase (mid-point ratio) | I4: Subscribers (conversion rate) | J4: Subscription revenue — Year 1 case | K4: Subscription revenue — Renewal case | L4: Renewal revenue minus Vercel+Supabase MID cost
A5: ='User Tiers'!B4 -> 1000 | B5: ='AWS (PRD sec 6.2)'!B6 -> 4400 | C5: ='AWS (PRD sec 6.2)'!B7 -> 7900 | D5: =AVERAGE(B5:C5) -> 6150 | E5: ='Vercel Cost Model'!B20+'Supabase Cost Model'!B20 -> 270.24645 | F5: ='Vercel Cost Model'!B21+'Supabase Cost Model'!B21 -> 810.73935 | G5: =AVERAGE(E5:F5) -> 540.4929 | H5: =D5/G5 -> 11.378503 | I5: ='Subscriber Revenue'!B6 -> 30 | J5: ='Subscriber Revenue'!B12 -> 553.5 | K5: ='Subscriber Revenue'!B13 -> 733.5 | L5: =K5-G5 -> 193.0071
A6: ='User Tiers'!C4 -> 10000 | B6: ='AWS (PRD sec 6.2)'!C6 -> 4400 | C6: ='AWS (PRD sec 6.2)'!C7 -> 7900 | D6: =AVERAGE(B6:C6) -> 6150 | E6: ='Vercel Cost Model'!C20+'Supabase Cost Model'!C20 -> 326.6805 | F6: ='Vercel Cost Model'!C21+'Supabase Cost Model'!C21 -> 980.0415 | G6: =AVERAGE(E6:F6) -> 653.361 | H6: =D6/G6 -> 9.4128667 | I6: ='Subscriber Revenue'!C6 -> 300 | J6: ='Subscriber Revenue'!C12 -> 5535 | K6: ='Subscriber Revenue'!C13 -> 7335 | L6: =K6-G6 -> 6681.639
A7: ='User Tiers'!D4 -> 50000 | B7: ='AWS (PRD sec 6.2)'!D6 -> 17400.842 | C7: ='AWS (PRD sec 6.2)'!D7 -> 29637.967 | D7: =AVERAGE(B7:C7) -> 23519.405 | E7: ='Vercel Cost Model'!D20+'Supabase Cost Model'!D20 -> 657.42058 | F7: ='Vercel Cost Model'!D21+'Supabase Cost Model'!D21 -> 1972.2617 | G7: =AVERAGE(E7:F7) -> 1314.8412 | H7: =D7/G7 -> 17.88764 | I7: ='Subscriber Revenue'!D6 -> 1500 | J7: ='Subscriber Revenue'!D12 -> 27675 | K7: ='Subscriber Revenue'!D13 -> 36675 | L7: =K7-G7 -> 35360.159
A8: ='User Tiers'!E4 -> 100000 | B8: ='AWS (PRD sec 6.2)'!E6 -> 23000 | C8: ='AWS (PRD sec 6.2)'!E7 -> 39000 | D8: =AVERAGE(B8:C8) -> 31000 | E8: ='Vercel Cost Model'!E20+'Supabase Cost Model'!E20 -> 1601.4938 | F8: ='Vercel Cost Model'!E21+'Supabase Cost Model'!E21 -> 4804.4812 | G8: =AVERAGE(E8:F8) -> 3202.9875 | H8: =D8/G8 -> 9.6784642 | I8: ='Subscriber Revenue'!E6 -> 3000 | J8: ='Subscriber Revenue'!E12 -> 55350 | K8: ='Subscriber Revenue'!E13 -> 73350 | L8: =K8-G8 -> 70147.012
A9: ='User Tiers'!F4 -> 1000000 | B9: ='AWS (PRD sec 6.2)'!F6 -> 100000 | C9: ='AWS (PRD sec 6.2)'!F7 -> 180000 | D9: =AVERAGE(B9:C9) -> 140000 | E9: ='Vercel Cost Model'!F20+'Supabase Cost Model'!F20 -> 34609.357 | F9: ='Vercel Cost Model'!F21+'Supabase Cost Model'!F21 -> 103828.07 | G9: =AVERAGE(E9:F9) -> 69218.715 | H9: =D9/G9 -> 2.0225744 | I9: ='Subscriber Revenue'!F6 -> 30000 | J9: ='Subscriber Revenue'!F12 -> 553500 | K9: ='Subscriber Revenue'!F13 -> 733500 | L9: =K9-G9 -> 664281.29
A11: Reading the ratio (col H): a value above 1.00x means the PRD's AWS estimate costs more than the Vercel+Supabase estimate at that tier; below 1.00x means AWS would be cheaper.
A13: Why there may be no clean single “crossover point”:
A14: AWS as modeled in the PRD (§8.2) is always-on EC2 + RDS + ElastiCache — cost is dominated by fixed instance sizing, so it doesn't fall much below the Pilot's own floor at low user counts, and climbs in discrete instance-size steps rather than smoothly. Vercel and Supabase are both metered — pay for requests/compute-seconds/storage actually used — so their cost scales toward zero at low usage and rises continuously with it. That's a difference in cost SHAPE, not just level: whether AWS "wins" at a given scale depends heavily on how request/compute-intensive the app actually is per user, which is the least certain input in this whole model (see the Vercel/Supabase technical assumptions — none of them come from the PRD).
A16: Column L reads negative at low registered-user counts because a 3% conversion rate on a small user base yields very few subscribers — e.g. only ~30 subscribers at the 1,000-registered-user tier. The infra cost itself (column G) is small in absolute terms throughout (see the Vercel/Supabase Cost Model tabs); the real breakeven question is 'how many subscribers', not 'how many registered users' — see the Breakeven note on the Subscriber Revenue tab and the new Assumptions section 4 for the conversion-rate input driving this.

Sheet AWS Activate Credits
A1: AWS Activate credits — what actually determines the amount
A2: Sources: aws.amazon.com/startups (fetched 2026-08-14) and third-party program-tier summaries current as of mid-2026.
A4: Headline
A5: Up to $200,000 in AWS Activate Credits, redeemable on 200+ AWS services including third-party Bedrock models; credits typically last up to 2 years.
A7: Tier | B7: Typical amount | C7: Qualification — NOT a function of your registered-user count
A8: Founders (self-serve) | B8: $1,000–$5,000 | C8: Any founder can self-apply directly on aws.amazon.com/startups/join. Requires: self-funded/bootstrapped, not previously affiliated with an AWS Activate Provider, and no prior AWS credits of equal or greater value. Available immediately, regardless of scale.
A9: Portfolio | B9: $25,000–$100,000 | C9: Requires an Organization ID from an accredited AWS Activate Provider — a VC firm, accelerator, or incubator you're backed by or a member of. This is the actual gate on this tier, not usage.
A10: Generative AI / scale tiers | B10: up to $200,000+ | C10: Tied to committed usage of AWS AI services (Bedrock, SageMaker, Trainium) — not relevant to WYP unless an AI feature is added later.
A12: What this means for Jim's question
A13: There is no published “at N registered users, you unlock $X in credits” formula — the tier gate is funding/backing status (bootstrapped vs. VC/accelerator-backed), not traffic. A working beta with real usage is a genuinely useful talking point once you're in a conversation with an AWS startup rep (it's evidence the product works and infra needs are real), and matters more for negotiated custom/Enterprise deals at real scale, but it doesn't move you between the published tiers above on its own. The Founders tier ($1K–$5K) is available today, with zero users, at zero cost to apply.
